PySide6-stubs/Qt3DAnimation.pyi
PySide6-stubs/Qt3DCore.pyi
PySide6-stubs/Qt3DExtras.pyi
PySide6-stubs/Qt3DInput.pyi
PySide6-stubs/Qt3DLogic.pyi
PySide6-stubs/Qt3DRender.pyi
PySide6-stubs/QtBluetooth.pyi
PySide6-stubs/QtCharts.pyi
PySide6-stubs/QtConcurrent.pyi
PySide6-stubs/QtCore.pyi
PySide6-stubs/QtDBus.pyi
PySide6-stubs/QtDataVisualization.pyi
PySide6-stubs/QtDesigner.pyi
PySide6-stubs/QtGraphs.pyi
PySide6-stubs/QtGraphsWidgets.pyi
PySide6-stubs/QtGui.pyi
PySide6-stubs/QtHelp.pyi
PySide6-stubs/QtHttpServer.pyi
PySide6-stubs/QtLocation.pyi
PySide6-stubs/QtMultimedia.pyi
PySide6-stubs/QtMultimediaWidgets.pyi
PySide6-stubs/QtNetwork.pyi
PySide6-stubs/QtNetworkAuth.pyi
PySide6-stubs/QtNfc.pyi
PySide6-stubs/QtOpenGL.pyi
PySide6-stubs/QtOpenGLWidgets.pyi
PySide6-stubs/QtPdf.pyi
PySide6-stubs/QtPdfWidgets.pyi
PySide6-stubs/QtPositioning.pyi
PySide6-stubs/QtPrintSupport.pyi
PySide6-stubs/QtQml.pyi
PySide6-stubs/QtQuick.pyi
PySide6-stubs/QtQuick3D.pyi
PySide6-stubs/QtQuickControls2.pyi
PySide6-stubs/QtQuickTest.pyi
PySide6-stubs/QtQuickWidgets.pyi
PySide6-stubs/QtRemoteObjects.pyi
PySide6-stubs/QtScxml.pyi
PySide6-stubs/QtSensors.pyi
PySide6-stubs/QtSerialBus.pyi
PySide6-stubs/QtSerialPort.pyi
PySide6-stubs/QtSpatialAudio.pyi
PySide6-stubs/QtSql.pyi
PySide6-stubs/QtStateMachine.pyi
PySide6-stubs/QtSvg.pyi
PySide6-stubs/QtSvgWidgets.pyi
PySide6-stubs/QtTest.pyi
PySide6-stubs/QtTextToSpeech.pyi
PySide6-stubs/QtUiTools.pyi
PySide6-stubs/QtWebChannel.pyi
PySide6-stubs/QtWebEngineCore.pyi
PySide6-stubs/QtWebEngineQuick.pyi
PySide6-stubs/QtWebEngineWidgets.pyi
PySide6-stubs/QtWebSockets.pyi
PySide6-stubs/QtWebView.pyi
PySide6-stubs/QtWidgets.pyi
PySide6-stubs/QtXml.pyi
PySide6-stubs/__init__.pyi
PySide6-stubs/_config.pyi
PySide6-stubs/_git_pyside_version.pyi
PySide6-stubs/py.typed
PySide6-stubs/QtAsyncio/__init__.pyi
PySide6-stubs/QtAsyncio/events.pyi
PySide6-stubs/QtAsyncio/futures.pyi
PySide6-stubs/QtAsyncio/tasks.pyi
PySide6-stubs/scripts/__init__.pyi
types_pyside6-6.10.1.1.dist-info/METADATA
types_pyside6-6.10.1.1.dist-info/WHEEL
types_pyside6-6.10.1.1.dist-info/RECORD
