Metadata-Version: 2.4
Name: types-PySide6
Version: 6.10.1.1
Summary: The most accurate stubs for PySide6
Author: Chad Dombrova
License-Expression: MIT
Keywords: 3d,CG,VFX,animation,games,graphics
Classifier: Development Status :: 4 - Beta
Classifier: Intended Audience :: Developers
Classifier: License :: OSI Approved :: MIT License
Classifier: Operating System :: OS Independent
Classifier: Programming Language :: Python :: 2
Classifier: Programming Language :: Python :: 3
Classifier: Typing :: Stubs Only
